fw_gear_relabel_container/__init__.py
fw_gear_relabel_container/get_inputs.py
fw_gear_relabel_container/main.py
fw_gear_relabel_container/parser.py
fw_gear_relabel_container/run_1.py
fw_gear_relabel_container/run_2.py
fw_gear_relabel_container-0.5.3.dist-info/LICENSE
fw_gear_relabel_container-0.5.3.dist-info/METADATA
fw_gear_relabel_container-0.5.3.dist-info/WHEEL
fw_gear_relabel_container-0.5.3.dist-info/RECORD
