Metadata-Version: 2.1
Name: fw-gear-relabel-container
Version: 0.5.3
Summary: Change container labels in preparation for curate-bids gear
Home-page: https://gitlab.com/flywheel-io/scientific-solutions/gears/relabel-container
License: MIT
Keywords: Flywheel,Gears
Author: Flywheel
Author-email: support@flywheel.io
Requires-Python: >=3.11,<4.0
Classifier: License :: OSI Approved :: MIT License
Classifier: Programming Language :: Python :: 3
Classifier: Programming Language :: Python :: 3.11
Classifier: Programming Language :: Python :: 3.12
Classifier: Topic :: Scientific/Engineering
Requires-Dist: flywheel-gear-toolkit (>=0.6,<0.7)
Requires-Dist: flywheel-sdk (>=16.8.0,<17.0.0)
Requires-Dist: fw-client (>=0.7.4,<0.8.0)
Requires-Dist: pandas (>=2.2.1,<3.0.0)
Project-URL: Repository, https://gitlab.com/flywheel-io/scientific-solutions/gears/relabel-container
